tool_call_models/__init__.py
tool_call_models/base.py
tool_call_models/cards.py
tool_call_models/home_balance.py
tool_call_models/payment.py
tool_call_models/paynet.py
tool_call_models/smartbazar.py
tool_call_models/weather.py
tool_call_models-0.1.40.dist-info/METADATA
tool_call_models-0.1.40.dist-info/WHEEL
tool_call_models-0.1.40.dist-info/RECORD
