Metadata-Version: 2.4
Name: tool_call_models
Version: 0.1.40
Summary: A simple package of models used between two services in order to achieve SDUI widgets using LLMs.
License-Expression: MIT
Author: Aslon Khamidov
Author-email: hamidovaslon1@gmail.com
Requires-Python: >=3.11
Classifier: Programming Language :: Python :: 3
Classifier: Programming Language :: Python :: 3.11
Classifier: Programming Language :: Python :: 3.12
Classifier: Programming Language :: Python :: 3.13
Classifier: Programming Language :: Python :: 3.14
Requires-Dist: pydantic
Project-URL: Homepage, https://github.com/Guide-Me-Tech/tool_models
